CHANGES.rst
LICENSE.txt
MANIFEST.in
README.rst
buildout.cfg
setup.py
src/buildout/__init__.py
src/buildout.wheel.egg-info/PKG-INFO
src/buildout.wheel.egg-info/SOURCES.txt
src/buildout.wheel.egg-info/dependency_links.txt
src/buildout.wheel.egg-info/entry_points.txt
src/buildout.wheel.egg-info/namespace_packages.txt
src/buildout.wheel.egg-info/not-zip-safe
src/buildout.wheel.egg-info/requires.txt
src/buildout.wheel.egg-info/top_level.txt
src/buildout/wheel/__init__.py
src/buildout/wheel/namespace_stub.py
src/buildout/wheel/tests/__init__.py
src/buildout/wheel/tests/testwheel.py
src/buildout/wheel/tests/samples/getvals.py
src/buildout/wheel/tests/samples/demo/demo.py
src/buildout/wheel/tests/samples/demo/setup.py
src/buildout/wheel/tests/samples/extdemo/extdemo.c
src/buildout/wheel/tests/samples/extdemo/extdemo.h
src/buildout/wheel/tests/samples/extdemo/setup.py