Metadata-Version: 1.1
Name: buildout.wheel
Version: 0.2.0
Summary: Experimental Buildout extension to provide wheel support
Home-page: https://github.com/buildout/buildout.wheel
Author: Jim Fulton
Author-email: jim@jimfulton.info
License: MIT License
Keywords: development build
Platform: UNKNOWN
Classifier: Development Status :: 5 - Production/Stable
Classifier: Framework :: Buildout
Classifier: Intended Audience :: Developers
Classifier: License :: OSI Approved :: MIT License
Classifier: Programming Language :: Python
Classifier: Programming Language :: Python :: 2
Classifier: Programming Language :: Python :: 2.7
Classifier: Programming Language :: Python :: 3
Classifier: Programming Language :: Python :: 3.4
Classifier: Programming Language :: Python :: 3.5
Classifier: Programming Language :: Python :: 3.6
Classifier: Topic :: Software Development :: Build Tools
Classifier: Topic :: Software Development :: Libraries :: Python Modules
